djangelo/__init__.py
djangelo/_django_settings.py
djangelo/_elo_implementation.py
djangelo/apps.py
djangelo/models.py
djangelo/signals.py
djangelo/utils.py
djangelo/migrations/0001_initial.py
djangelo/migrations/0002_auto_20201220_1900.py
djangelo/migrations/__init__.py
djangelo-0.1.4.data/data/libdjangelo/libdjangelo.so
djangelo-0.1.4.dist-info/LICENSE
djangelo-0.1.4.dist-info/METADATA
djangelo-0.1.4.dist-info/WHEEL
djangelo-0.1.4.dist-info/entry_points.txt
djangelo-0.1.4.dist-info/top_level.txt
djangelo-0.1.4.dist-info/RECORD
