Metadata-Version: 2.1
Name: djangelo
Version: 0.1.4
Summary: Tracking and rating Django Model activities with ELO system 
Home-page: https://gitlab.com/agustinjimenez/djangelo
Author: Agustin Jimenez
Author-email: agustin.j@zohomail.com
License: APACHE 2.0
Keywords: django elo rating tracking plugin
Platform: UNKNOWN
Classifier: Development Status :: 1 - Planning
Classifier: Framework :: Django :: 3.0
Classifier: Framework :: Django :: 3.1
Classifier: Intended Audience :: Developers
Classifier: Intended Audience :: System Administrators
Classifier: Intended Audience :: Telecommunications Industry
Classifier: License :: OSI Approved :: Apache Software License
Classifier: Programming Language :: Python :: 3
Classifier: Programming Language :: Python :: 3.0
Classifier: Programming Language :: Python :: 3.1
Classifier: Programming Language :: Python :: 3.10
Classifier: Programming Language :: Python :: 3.2
Classifier: Programming Language :: Python :: 3.3
Classifier: Programming Language :: Python :: 3.4
Classifier: Programming Language :: Python :: 3.5
Classifier: Programming Language :: Python :: 3.6
Classifier: Programming Language :: Python :: 3.7
Classifier: Programming Language :: Python :: 3.8
Classifier: Programming Language :: Python :: 3.9
Classifier: Topic :: Internet :: WWW/HTTP
Classifier: Topic :: Internet :: WWW/HTTP :: Dynamic Content
Classifier: Topic :: Software Development
Classifier: Topic :: Software Development :: Libraries :: Python Modules
Requires-Dist: Django (~=3.0.2)
Provides-Extra: dev
Requires-Dist: bandit (~=1.6.2) ; extra == 'dev'
Requires-Dist: djangorestframework (~=3.11.0) ; extra == 'dev'
Requires-Dist: flake8 (~=3.7.9) ; extra == 'dev'
Requires-Dist: flake8-html (~=0.4.1) ; extra == 'dev'
Requires-Dist: pytest (~=5.4.3) ; extra == 'dev'
Requires-Dist: pytest-django (~=3.9.0) ; extra == 'dev'
Requires-Dist: pytest-cov (~=2.10.0) ; extra == 'dev'
Requires-Dist: pytest-flake8 (~=1.0.6) ; extra == 'dev'
Requires-Dist: pytest-html (~=2.1.1) ; extra == 'dev'
